psy_reg/__init__.py
psy_reg/_version.py
psy_reg/plotters.py
psy_reg/plugin.py
psy_reg/utils.py
psy_reg-1.5.0.dist-info/CC-BY-4.0.txt
psy_reg-1.5.0.dist-info/CC0-1.0.txt
psy_reg-1.5.0.dist-info/LGPL-3.0-only.txt
psy_reg-1.5.0.dist-info/METADATA
psy_reg-1.5.0.dist-info/WHEEL
psy_reg-1.5.0.dist-info/entry_points.txt
psy_reg-1.5.0.dist-info/top_level.txt
psy_reg-1.5.0.dist-info/RECORD
